iglovikov_helper_functions/__init__.py
iglovikov_helper_functions/config_parsing/__init__.py
iglovikov_helper_functions/config_parsing/from_py.py
iglovikov_helper_functions/config_parsing/utils.py
iglovikov_helper_functions/data_processing/__init__.py
iglovikov_helper_functions/data_processing/cityscapes/__init__.py
iglovikov_helper_functions/data_processing/cityscapes/parse_cityscapes.py
iglovikov_helper_functions/data_processing/corrupt_dataset/__init__.py
iglovikov_helper_functions/data_processing/corrupt_dataset/transform.py
iglovikov_helper_functions/data_processing/gleason2019/__init__.py
iglovikov_helper_functions/data_processing/gleason2019/prepare_the_data.py
iglovikov_helper_functions/data_processing/image_processing/__init__.py
iglovikov_helper_functions/data_processing/image_processing/png2jpg.py
iglovikov_helper_functions/data_processing/kaggle_severstal/__init__.py
iglovikov_helper_functions/data_processing/kaggle_severstal/preprocess_data.py
iglovikov_helper_functions/data_processing/ms_celeb_1m/__init__.py
iglovikov_helper_functions/data_processing/ms_celeb_1m/clean.py
iglovikov_helper_functions/data_processing/ms_celeb_1m/crop_and_align.py
iglovikov_helper_functions/data_processing/ms_celeb_1m/parse_data.py
iglovikov_helper_functions/data_processing/open_images/__init__.py
iglovikov_helper_functions/data_processing/open_images/instance2coco.py
iglovikov_helper_functions/data_processing/prepare_cloths_segmentation/__init__.py
iglovikov_helper_functions/data_processing/prepare_cloths_segmentation/prepare_imaterialist2019.py
iglovikov_helper_functions/data_processing/prepare_people_segmentation/__init__.py
iglovikov_helper_functions/data_processing/prepare_people_segmentation/prepare_coco.py
iglovikov_helper_functions/data_processing/prepare_people_segmentation/prepare_matting.py
iglovikov_helper_functions/data_processing/prepare_people_segmentation/prepare_pascal_voc.py
iglovikov_helper_functions-0.0.53.dist-info/LICENSE
iglovikov_helper_functions-0.0.53.dist-info/METADATA
iglovikov_helper_functions-0.0.53.dist-info/WHEEL
iglovikov_helper_functions-0.0.53.dist-info/top_level.txt
iglovikov_helper_functions-0.0.53.dist-info/RECORD
